auto_schema/__init__.py
auto_schema/change_type.py
auto_schema/clause_text.py
auto_schema/command.py
auto_schema/compare.py
auto_schema/config.py
auto_schema/diff.py
auto_schema/env.py
auto_schema/ops.py
auto_schema/ops_impl.py
auto_schema/renderers.py
auto_schema/runner.py
auto_schema/script.py.mako
auto_schema/util.py
auto_schema/cli/__init__.py
tests/__init__.py
tests/conftest.py
tests/runner_test.py
auto_schema_test-0.0.7.dist-info/LICENSE
auto_schema_test-0.0.7.dist-info/METADATA
auto_schema_test-0.0.7.dist-info/WHEEL
auto_schema_test-0.0.7.dist-info/entry_points.txt
auto_schema_test-0.0.7.dist-info/top_level.txt
auto_schema_test-0.0.7.dist-info/RECORD
