Metadata-Version: 2.1
Name: auto-schema-test
Version: 0.0.7
Summary: auto schema for a db
Home-page: https://github.com/lolopinto/ent/tree/master/python/auto_schema
Author: Ola Okelola
Author-email: email@email.com
License: UNKNOWN
Platform: UNKNOWN
Classifier: Programming Language :: Python :: 3
Classifier: License :: OSI Approved :: MIT License
Classifier: Operating System :: OS Independent
Requires-Python: >=3.6
License-File: LICENSE
Requires-Dist: sqlalchemy (==1.3.19)
Requires-Dist: alembic (==1.4.2)
Requires-Dist: datetime (==4.3)
Requires-Dist: psycopg2 (==2.8.6)
Requires-Dist: autopep8 (==1.5.4)
Requires-Dist: python-dateutil (==2.8.2)
